{
    "info": {
        "region": "212-400-forma.reg", 
        "description": "JSON data file for stationary bowshock arcs", 
        "history": [
            "Initially created by find-xy-shell.py: <will@mac> 2014-05-13 09:42", 
            "Circle fits added by fit-circle-shell.py: <will@mac> 2014-05-13 09:42", 
            "Image Bally_06 added by extract-image.py: <will@mac> 2014-05-13 09:42", 
            "Shell data for Bally_06 added/modified by arc_brightness.py: <will@mac> 2014-05-13 09:42", 
            "Plot limits modified for Bally_06 plot-image.py: <will@mac> 2014-05-13 19:18", 
            "Plot limits modified for Bally_06 plot-image.py: <will@mac> 2014-05-13 19:19", 
            "Image Robberto_WFPC2_f656n_39 added by extract-image.py: <angel@crya> 2014-06-25 16:05", 
            "Shell data for Robberto_WFPC2_f656n_39 added/modified by arc_brightness.py: <angel@crya> 2014-06-25 16:06", 
            "Shell data for Bally_06 added/modified by arc_brightness.py: <angel@crya> 2014-06-25 16:06", 
            "Plot limits modified for Robberto_WFPC2_f656n_39 plot-image.py: <angel@crya> 2014-07-02 23:20", 
            "Image Robberto_WFPC2_39_f656n added by extract-image.py: <angel@crya> 2014-07-05 17:39", 
            "Shell data for Robberto_WFPC2_39_f656n added/modified by arc_brightness.py: <angel@crya> 2014-07-05 17:43", 
            "Shell data for Robberto_WFPC2_f656n_39 added/modified by arc_brightness.py: <angel@crya> 2014-07-05 17:43", 
            "Shell data for Bally_06 added/modified by arc_brightness.py: <angel@crya> 2014-07-05 17:43", 
            "Plot limits modified for Robberto_WFPC2_39_f656n plot-image.py: <angel@crya> 2014-07-05 17:47", 
            "Image WFC_mosaic_f656 added by extract-image.py: <angel@crya> 2014-07-16 20:29", 
            "Shell data for Robberto_WFPC2_39_f656n added/modified by arc_brightness.py: <angel@crya> 2014-07-16 20:30", 
            "Shell data for WFC_mosaic_f656 added/modified by arc_brightness.py: <angel@crya> 2014-07-16 20:30", 
            "Shell data for Robberto_WFPC2_f656n_39 added/modified by arc_brightness.py: <angel@crya> 2014-07-16 20:30", 
            "Shell data for Bally_06 added/modified by arc_brightness.py: <angel@crya> 2014-07-16 20:30", 
            "Plot limits modified for WFC_mosaic_f656 plot-image.py: <angel@crya> 2014-07-16 20:33", 
            "Image WFC_mosaic_f658 added by extract-image.py: <angel@crya> 2014-07-16 20:35", 
            "Shell data for Robberto_WFPC2_39_f656n added/modified by arc_brightness.py: <angel@crya> 2014-07-16 20:36", 
            "Shell data for WFC_mosaic_f656 added/modified by arc_brightness.py: <angel@crya> 2014-07-16 20:36", 
            "Shell data for WFC_mosaic_f658 added/modified by arc_brightness.py: <angel@crya> 2014-07-16 20:36", 
            "Shell data for Robberto_WFPC2_f656n_39 added/modified by arc_brightness.py: <angel@crya> 2014-07-16 20:36", 
            "Shell data for Bally_06 added/modified by arc_brightness.py: <angel@crya> 2014-07-16 20:36", 
            "Plot limits modified for WFC_mosaic_f658 plot-image.py: <angel@crya> 2014-07-16 20:38", 
            "Shell data for Robberto_WFPC2_39_f656n added/modified by arc_brightness.py: <angel@crya> 2014-07-22 17:32", 
            "Shell data for WFC_mosaic_f656 added/modified by arc_brightness.py: <angel@crya> 2014-07-22 17:32", 
            "Shell data for WFC_mosaic_f658 added/modified by arc_brightness.py: <angel@crya> 2014-07-22 17:32", 
            "Shell data for Robberto_WFPC2_f656n_39 added/modified by arc_brightness.py: <angel@crya> 2014-07-22 17:32", 
            "Shell data for Bally_06 added/modified by arc_brightness.py: <angel@crya> 2014-07-22 17:33", 
            "Image WFC_mosaic_f547 added by extract-image.py: <angel@crya> 2014-07-30 17:39", 
            "Shell data for Robberto_WFPC2_39_f656n added/modified by arc_brightness.py: <angel@crya> 2014-07-30 17:40", 
            "Shell data for WFC_mosaic_f656 added/modified by arc_brightness.py: <angel@crya> 2014-07-30 17:40", 
            "Shell data for WFC_mosaic_f658 added/modified by arc_brightness.py: <angel@crya> 2014-07-30 17:40", 
            "Shell data for Robberto_WFPC2_f656n_39 added/modified by arc_brightness.py: <angel@crya> 2014-07-30 17:40", 
            "Shell data for WFC_mosaic_f547 added/modified by arc_brightness.py: <angel@crya> 2014-07-30 17:40", 
            "Shell data for Bally_06 added/modified by arc_brightness.py: <angel@crya> 2014-07-30 17:40", 
            "Image WFC_mosaic_f502 added by extract-image.py: <angel@crya> 2014-07-31 16:43", 
            "Shell data for Robberto_WFPC2_39_f656n added/modified by arc_brightness.py: <angel@crya> 2014-07-31 16:44", 
            "Shell data for WFC_mosaic_f656 added/modified by arc_brightness.py: <angel@crya> 2014-07-31 16:44", 
            "Shell data for WFC_mosaic_f658 added/modified by arc_brightness.py: <angel@crya> 2014-07-31 16:44", 
            "Shell data for Robberto_WFPC2_f656n_39 added/modified by arc_brightness.py: <angel@crya> 2014-07-31 16:44", 
            "Shell data for WFC_mosaic_f502 added/modified by arc_brightness.py: <angel@crya> 2014-07-31 16:44", 
            "Shell data for WFC_mosaic_f547 added/modified by arc_brightness.py: <angel@crya> 2014-07-31 16:44", 
            "Shell data for Bally_06 added/modified by arc_brightness.py: <angel@crya> 2014-07-31 16:44"
        ]
    }, 
    "star": {
        "Dec_dg": -5.4001277777777785, 
        "D": 80.98826203256895, 
        "PA": 297.92877200656574, 
        "RA": "5:35:21.181", 
        "Dec": "-5:24:00.46", 
        "RA_dg": 83.83825416666666, 
        "id": "212-400"
    }, 
    "help": {
        "brightness": {
            "shell": "Trimean brightness and interquartile (difference between quartiles) of shell", 
            "shell center": "Trimean brightness and interquartile (difference between quartiles) of shell center", 
            "background": "Trimean brightness and interquartile (difference between quartiles) of background"
        }, 
        "arcs": {
            "PA0": "[deg] Position angle of symmetry axis", 
            "R0": "[arcsec] Radius along symmetry axis", 
            "h": "[arcsec] Bowshock width along symmetry axis", 
            "Y": "(list) [arcsec] Offsets from star perpendicular to axis of shell points", 
            "R": "(list) [arcsec] Radii of shell points from star", 
            "x": "(list) [arcsec] RA offsets from star of shell points", 
            "y": "(list) [arcsec] Dec offsets from star of shell points", 
            "X": "(list) [arcsec] Offsets from star parallel to axis of shell points", 
            "theta": "(list) [deg] Angle from axis of shell points"
        }, 
        "star": {
            "Dec_dg": "[deg] Declination of source", 
            "D": "[arcsec] Distance of th^1 C from source", 
            "PA": "[deg] Position Angle of th^1 C from source", 
            "RA": "[HH:MM:SS] Right ascension of source", 
            "Dec": "[deg:arcmin:arcsec] Declination of source", 
            "RA_dg": "[deg] Right ascension of source", 
            "id": "Source identifier deduced from region filename"
        }, 
        "thickness": {
            "h0": "Shell thickness on axis: h0 = R0(outer) - R0(inner)"
        }
    }, 
    "WFC_mosaic_f656": {
        "shell": {
            "N": 26, 
            "value": 607.757698059082, 
            "delta": 15.862152099609375
        }, 
        "extracted FITS file": "212-400-WFC_mosaic_f656-extract.fits", 
        "original FITS file": "$SMALL_FITS_DIR/mosaicf656-fixw-align.fits", 
        "filter": "F547M", 
        "binned": {
            "theta": [
                -48.0, 
                -24.0, 
                0.0, 
                24.0, 
                48.0
            ], 
            "shell": [
                608.62072372436523, 
                603.64483642578125, 
                603.29374694824219, 
                613.41172790527344, 
                630.88807678222656
            ], 
            "background": [
                605.91907501220703, 
                600.00853729248047, 
                606.66306304931641, 
                623.05137634277344, 
                644.46720123291016
            ], 
            "background N": [
                10, 
                7, 
                8, 
                6, 
                8
            ], 
            "background sigma": [
                4.2101324168141101, 
                2.9405683009035286, 
                1.332590998551521, 
                2.1305167622372982, 
                9.8271714493640516
            ]
        }, 
        "camera": "WFPC2", 
        "plot limits": {
            "max": 655.3441543579102, 
            "min": 561.1349487304688
        }, 
        "shell center": {
            "N": 12, 
            "value": 607.3948402404785, 
            "delta": 10.589492797851562
        }, 
        "background": {
            "N": 29, 
            "value": 610.5873413085938, 
            "delta": 16.484130859375
        }, 
        "date": "1995-03-21"
    }, 
    "WFC_mosaic_f658": {
        "shell": {
            "N": 26, 
            "value": 286.8218517303467, 
            "delta": 12.313163757324219
        }, 
        "extracted FITS file": "212-400-WFC_mosaic_f658-extract.fits", 
        "original FITS file": "$SMALL_FITS_DIR/mosaicf658-fixw-align.fits", 
        "filter": "F547M", 
        "binned": {
            "theta": [
                -48.0, 
                -24.0, 
                0.0, 
                24.0, 
                48.0
            ], 
            "shell": [
                286.90056800842285, 
                283.20834350585938, 
                285.13527679443359, 
                291.20924758911133, 
                300.62983703613281
            ], 
            "background": [
                279.26122665405273, 
                277.62101745605469, 
                277.8026065826416, 
                287.3150806427002, 
                303.66635322570801
            ], 
            "background N": [
                10, 
                7, 
                8, 
                6, 
                8
            ], 
            "background sigma": [
                2.4156082105650509, 
                2.7048169929346737, 
                2.3680156749024963, 
                3.2752317724139655, 
                10.287922620228141
            ]
        }, 
        "camera": "WFPC2", 
        "plot limits": {
            "max": 323.76134300231934, 
            "min": 256.64727783203125
        }, 
        "shell center": {
            "N": 12, 
            "value": 286.7015628814697, 
            "delta": 7.481651306152344
        }, 
        "background": {
            "N": 29, 
            "value": 280.13568115234375, 
            "delta": 7.8294677734375
        }, 
        "date": "1995-03-21"
    }, 
    "WFC_mosaic_f547": {
        "shell": {
            "N": 26, 
            "value": 32.29320955276489, 
            "delta": 1.1235923767089844
        }, 
        "extracted FITS file": "212-400-WFC_mosaic_f547-extract.fits", 
        "original FITS file": "$SMALL_FITS_DIR/mosaicf547-fixw-align.fits", 
        "filter": "F547M", 
        "binned": {
            "theta": [
                -48.0, 
                -24.0, 
                0.0, 
                24.0, 
                48.0
            ], 
            "shell": [
                31.978322625160217, 
                30.88310980796814, 
                32.361421704292297, 
                33.115106105804443, 
                33.507191896438599
            ], 
            "background": [
                32.533166885375977, 
                32.508301734924316, 
                32.224049091339111, 
                32.886101961135864, 
                34.332327127456665
            ], 
            "background N": [
                8, 
                9, 
                7, 
                10, 
                10
            ], 
            "background sigma": [
                0.5059965998956325, 
                0.48021518886559639, 
                0.3748937275177649, 
                0.78706332591906369, 
                0.85896679616812899
            ]
        }, 
        "camera": "WFPC2", 
        "shell center": {
            "N": 13, 
            "value": 32.09633493423462, 
            "delta": 0.9151668548583984
        }, 
        "background": {
            "N": 31, 
            "value": 32.60928201675415, 
            "delta": 0.9092502593994141
        }, 
        "date": "1995-03-21"
    }, 
    "Robberto_WFPC2_39_f656n": {
        "shell": {
            "N": 125, 
            "value": 0.33292609453201294, 
            "delta": 0.011389732360839844
        }, 
        "extracted FITS file": "212-400-Robberto_WFPC2_39_f656n-extract.fits", 
        "original FITS file": "$LARGE_FITS_DIR/wfpc2/hlsp_orion_hst_wfpc2_39_f656n_v1_sci.fits", 
        "filter": "F656N", 
        "binned": {
            "theta": [
                -57.5, 
                -52.5, 
                -47.5, 
                -42.5, 
                -37.5, 
                -32.5, 
                -27.5, 
                -22.5, 
                -17.5, 
                -12.5, 
                -7.5, 
                -2.5, 
                2.5, 
                7.5, 
                12.5, 
                17.5, 
                22.5, 
                27.5, 
                32.5, 
                37.5, 
                42.5, 
                47.5, 
                52.5, 
                57.5
            ], 
            "shell": [
                0.32224845886230469, 
                0.32341020181775093, 
                0.32787564769387245, 
                0.32874833047389984, 
                0.32894988171756268, 
                0.33005014806985855, 
                0.33111316710710526, 
                0.32972445711493492, 
                0.32439884915947914, 
                0.3230731412768364, 
                0.3232913576066494, 
                0.32947909273207188, 
                0.32952918112277985, 
                0.33109558932483196, 
                0.33280915021896362, 
                0.3322986513376236, 
                0.33293105661869049, 
                0.33536293730139732, 
                0.33576309494674206, 
                0.33638931065797806, 
                0.3370831273496151, 
                0.33868656866252422, 
                0.34291662648320198, 
                0.35166379436850548
            ], 
            "background": [
                0.32921263575553894, 
                0.32832611352205276, 
                0.33290134556591511, 
                0.32970580831170082, 
                0.32899878919124603, 
                0.32706815004348755, 
                0.32570146769285202, 
                0.32459466904401779, 
                0.32632672041654587, 
                0.32550586014986038, 
                0.32621238008141518, 
                0.32818255573511124, 
                0.32837308570742607, 
                0.32947471365332603, 
                0.33100124821066856, 
                0.33636930584907532, 
                0.33956857770681381, 
                0.3405618742108345, 
                0.3427455723285675, 
                0.34467631578445435, 
                0.34768887236714363, 
                0.35033901780843735, 
                0.35551105067133904, 
                0.35793956927955151
            ], 
            "background N": [
                11, 
                9, 
                8, 
                7, 
                9, 
                7, 
                9, 
                8, 
                8, 
                9, 
                8, 
                8, 
                8, 
                8, 
                7, 
                9, 
                9, 
                6, 
                12, 
                9, 
                10, 
                9, 
                10, 
                8
            ], 
            "background sigma": [
                0.0012436748935066814, 
                0.0010406669602201339, 
                0.0016098745616070715, 
                0.0024865434109588454, 
                0.0049803110676663797, 
                0.0018558137351111707, 
                0.0018812421964467692, 
                0.0014142731371500285, 
                0.0047268328303649099, 
                0.0026690605554627969, 
                0.0017647816109292991, 
                0.0010889501072652694, 
                0.00045433215236019645, 
                0.0020227998558801736, 
                0.0047160958779677766, 
                0.010241329372283338, 
                0.0016247483336263521, 
                0.0022386656210497081, 
                0.00094252105276279509, 
                0.0018906315066706003, 
                0.0030693544659230157, 
                0.0088857118084139479, 
                0.0072066601229518858, 
                0.0032878658073262059
            ]
        }, 
        "camera": "WFPC2", 
        "plot limits": {
            "max": 0.36709529161453247, 
            "min": 0.2886772006750107
        }, 
        "shell center": {
            "N": 60, 
            "value": 0.3317376282066107, 
            "delta": 0.007932148873806
        }, 
        "background": {
            "N": 151, 
            "value": 0.33175303041934967, 
            "delta": 0.014358609914779663
        }, 
        "date": "2005-04-10"
    }, 
    "outer": {
        "PA0": 331.1821137314362, 
        "R0": 1.0749704131447926, 
        "xc": -0.1189417333280411, 
        "yc": 0.2139789205302082, 
        "y": [
            0.2900000000011005, 
            0.46000000000141483, 
            0.6099999999999994, 
            0.8600000000008379, 
            0.9700000000023579, 
            1.0400000000004184
        ], 
        "PAc": 150.93218882201302, 
        "X": [
            0.707579335417277, 
            0.8421292615111966, 
            0.9519577449791436, 
            1.0558237211369508, 
            1.0658210940802684, 
            1.0335738993791945
        ], 
        "Rc": 0.8306416720101565, 
        "Y": [
            -0.6845050380724672, 
            -0.5763923825428745, 
            -0.4648362567419902, 
            -0.134985218085561, 
            0.07504595221988292, 
            0.2788800487425732
        ], 
        "x": [
            -0.940805858323335, 
            -0.910939005502313, 
            -0.8661387266527703, 
            -0.627203905612555, 
            -0.44800278964139856, 
            -0.25386824745072617
        ], 
        "R": [
            0.9844875129000598, 
            1.0204949151009253, 
            1.0593848657629963, 
            1.064417558675675, 
            1.0684598726817256, 
            1.0705368219097247
        ], 
        "theta": [
            -44.05038888240415, 
            -34.389550824122836, 
            -26.026028021800975, 
            -7.28564182891127, 
            4.027628644582956, 
            15.10002106333292
        ]
    }, 
    "Robberto_WFPC2_f656n_39": {
        "shell": {
            "N": 121, 
            "value": 0.33784203976392746, 
            "delta": 0.014091044664382935
        }, 
        "extracted FITS file": "212-400-Robberto_WFPC2_f656n_39-extract.fits", 
        "original FITS file": "$LARGE_FITS_DIR/wfpc2/hlsp_orion_hst_wfpc2_39_f656n_v1_sci.fits", 
        "filter": "F656N", 
        "binned": {
            "theta": [
                -57.5, 
                -52.5, 
                -47.5, 
                -42.5, 
                -37.5, 
                -32.5, 
                -27.5, 
                -22.5, 
                -17.5, 
                -12.5, 
                -7.5, 
                -2.5, 
                2.5, 
                7.5, 
                12.5, 
                17.5, 
                22.5, 
                27.5, 
                32.5, 
                37.5, 
                42.5, 
                47.5, 
                52.5, 
                57.5
            ], 
            "shell": [
                0.33184678480029106, 
                0.32504577003419399, 
                0.32226713001728058, 
                0.32650886476039886, 
                0.32931751385331154, 
                0.33113974891602993, 
                0.33241110295057297, 
                0.33267996832728386, 
                0.33378507569432259, 
                0.33384892344474792, 
                0.33453908562660217, 
                0.33690885826945305, 
                0.33924305438995361, 
                0.34061739407479763, 
                0.34122811257839203, 
                0.34510581381618977, 
                0.34856335818767548, 
                NaN, 
                0.35065677762031555, 
                0.35274697467684746, 
                0.3519439809024334, 
                0.35710258968174458, 
                0.35686659067869186, 
                0.3536430224776268
            ], 
            "background": [
                0.33041011542081833, 
                0.3286181166768074, 
                0.32617298141121864, 
                0.32481905817985535, 
                0.32400905899703503, 
                0.32530597597360611, 
                0.32771876268088818, 
                0.32955528609454632, 
                0.32856892049312592, 
                0.32972686551511288, 
                0.34043532237410545, 
                0.34402617067098618, 
                0.34310559928417206, 
                0.34155774116516113, 
                0.34061379171907902, 
                0.34347556345164776, 
                0.34743601083755493, 
                0.35160156339406967, 
                0.35449548996984959, 
                0.35505466908216476, 
                0.35877242311835289, 
                0.35895218886435032, 
                0.36005137115716934, 
                0.36042092740535736
            ], 
            "background N": [
                11, 
                8, 
                8, 
                9, 
                8, 
                7, 
                8, 
                8, 
                7, 
                8, 
                7, 
                9, 
                7, 
                9, 
                8, 
                8, 
                7, 
                11, 
                6, 
                10, 
                11, 
                8, 
                9, 
                9
            ], 
            "background sigma": [
                0.0043600863730220733, 
                0.0017787772062864682, 
                0.002285181368523299, 
                0.0025466902276279741, 
                0.0037503721827047967, 
                0.0015413712588387331, 
                0.0021907083383005763, 
                0.0020964175711586691, 
                0.00023369440834749129, 
                0.0022616804773454161, 
                0.0061468721086171034, 
                0.002970446367400448, 
                0.0024933810380512586, 
                0.0063144326342468582, 
                0.0018490700011209956, 
                0.0015977789207893129, 
                0.0045726824489842506, 
                0.002106276346893692, 
                0.00074308658048496468, 
                0.0015786192048090366, 
                0.0026827468558949458, 
                0.0011662462229020424, 
                0.003680499145268511, 
                0.0037308037555736006
            ]
        }, 
        "camera": "WFPC2", 
        "plot limits": {
            "max": 0.385285135358572, 
            "min": 0.275967912748456
        }, 
        "shell center": {
            "N": 62, 
            "value": 0.3385479561984539, 
            "delta": 0.015579059720039368
        }, 
        "background": {
            "N": 148, 
            "value": 0.34062244929373264, 
            "delta": 0.02155151218175888
        }, 
        "date": "2005-04-10"
    }, 
    "thickness": {
        "h0": 0.23140934705219307
    }, 
    "inner": {
        "PA0": 335.47037661856814, 
        "R0": 0.8435610660925995, 
        "xc": -0.13817855724053202, 
        "yc": 0.2981329213445346, 
        "y": [
            0.25000000000083844, 
            0.4000000000026205, 
            0.6900000000005235, 
            0.7600000000017815, 
            0.7900000000027774, 
            0.8100000000013097
        ], 
        "PAc": 155.1332345223023, 
        "X": [
            0.5064284026105461, 
            0.618091150225183, 
            0.8385189939186768, 
            0.8526027384250414, 
            0.8178969813772698, 
            0.7554943090699832
        ], 
        "Rc": 0.5178614713884769, 
        "Y": [
            -0.5075627024952869, 
            -0.39094560966675057, 
            -0.1754486964703501, 
            -0.03770215271249217, 
            0.11060911651002628, 
            0.29552565703691525
        ], 
        "x": [
            -0.6720041844620979, 
            -0.612270479202044, 
            -0.5077364949014523, 
            -0.3882690843813448, 
            -0.23893482123121026, 
            -0.044800279040537884
        ], 
        "R": [
            0.7170004351009757, 
            0.7313515841949049, 
            0.8566775053983471, 
            0.8534359272312337, 
            0.8253422616110111, 
            0.8112379829644515
        ], 
        "theta": [
            -45.06409382553889, 
            -32.31354887004639, 
            -11.817869618310745, 
            -2.531973883349075, 
            7.701727157280835, 
            21.363877352770974
        ]
    }, 
    "WFC_mosaic_f502": {
        "shell": {
            "N": 26, 
            "value": 173.57625484466553, 
            "delta": 7.536624908447266
        }, 
        "extracted FITS file": "212-400-WFC_mosaic_f502-extract.fits", 
        "original FITS file": "$SMALL_FITS_DIR/mosaicf502-fixw-align.fits", 
        "filter": "F547M", 
        "binned": {
            "theta": [
                -48.0, 
                -24.0, 
                0.0, 
                24.0, 
                48.0
            ], 
            "shell": [
                169.00715637207031, 
                169.69196128845215, 
                172.54704761505127, 
                178.57456588745117, 
                180.59936714172363
            ], 
            "background": [
                169.01130294799805, 
                170.79673385620117, 
                176.17976379394531, 
                178.03528118133545, 
                184.45578575134277
            ], 
            "background N": [
                9, 
                8, 
                7, 
                10, 
                10
            ], 
            "background sigma": [
                0.5359886636649166, 
                1.5960494761235671, 
                1.0903809055884133, 
                3.7660004576011694, 
                1.6798270436540981
            ]
        }, 
        "camera": "WFPC2", 
        "shell center": {
            "N": 13, 
            "value": 172.5362319946289, 
            "delta": 7.9090576171875
        }, 
        "background": {
            "N": 32, 
            "value": 175.42248725891113, 
            "delta": 8.381134033203125
        }, 
        "date": "1995-03-21"
    }, 
    "Bally_06": {
        "shell": {
            "N": 100, 
            "value": 23.35837948322296, 
            "delta": 0.7481884956359863
        }, 
        "extracted FITS file": "212-400-Bally_06-extract.fits", 
        "original FITS file": "$LARGE_FITS_DIR/Bally-ACS/j8oc06010_wcs.fits", 
        "filter": "F658N", 
        "binned": {
            "theta": [
                -57.5, 
                -52.5, 
                -47.5, 
                -42.5, 
                -37.5, 
                -32.5, 
                -27.5, 
                -22.5, 
                -17.5, 
                -12.5, 
                -7.5, 
                -2.5, 
                2.5, 
                7.5, 
                12.5, 
                17.5, 
                22.5, 
                27.5, 
                32.5, 
                37.5, 
                42.5, 
                47.5, 
                52.5, 
                57.5
            ], 
            "shell": [
                23.033058166503906, 
                22.983482837677002, 
                23.071038365364075, 
                22.942804336547852, 
                23.388947486877441, 
                23.04020881652832, 
                23.157846450805664, 
                22.93764591217041, 
                22.975299835205078, 
                NaN, 
                23.133143305778503, 
                23.129419326782227, 
                23.328847169876099, 
                23.339447975158691, 
                23.448539018630981, 
                23.526961326599121, 
                23.460687875747681, 
                23.432521343231201, 
                23.702188491821289, 
                23.798773527145386, 
                23.81537938117981, 
                24.243266820907593, 
                24.365433573722839, 
                24.556450843811035
            ], 
            "background": [
                23.120085716247559, 
                23.23822021484375, 
                23.355599284172058, 
                23.176321506500244, 
                23.231029033660889, 
                23.050619602203369, 
                22.813050270080566, 
                22.872663736343384, 
                22.897206783294678, 
                23.044042110443115, 
                23.173380613327026, 
                23.034322023391724, 
                23.202823877334595, 
                23.215925931930542, 
                23.507831454277039, 
                23.89954137802124, 
                23.86059844493866, 
                23.936047554016113, 
                24.128334999084473, 
                24.157787799835205, 
                24.394726991653442, 
                24.772332668304443, 
                25.159912109375, 
                25.207600116729736
            ], 
            "background N": [
                8, 
                7, 
                6, 
                8, 
                6, 
                7, 
                7, 
                6, 
                9, 
                5, 
                7, 
                6, 
                7, 
                6, 
                8, 
                6, 
                8, 
                7, 
                7, 
                6, 
                8, 
                7, 
                8, 
                9
            ], 
            "background sigma": [
                0.29731266288506958, 
                0.30212069667949965, 
                0.35018300714817052, 
                0.091098843515697414, 
                0.20847538386112069, 
                0.31248048600806577, 
                0.10258976857005211, 
                0.080241354467784326, 
                0.080317706129275052, 
                0.088741839447085469, 
                0.093313748658757176, 
                0.15993622898804705, 
                0.15304761241799461, 
                0.25678194895057904, 
                0.43346640975849748, 
                0.19137119776754019, 
                0.26243020450132143, 
                0.20010639340994246, 
                0.15750075237845851, 
                0.11428712589436321, 
                0.09757954426463733, 
                0.37379935370306444, 
                0.1771620121721498, 
                0.077506833850690446
            ]
        }, 
        "camera": "ACS", 
        "plot limits": {
            "max": 33.0, 
            "min": 20.0
        }, 
        "shell center": {
            "N": 49, 
            "value": 23.351532459259033, 
            "delta": 0.40190696716308594
        }, 
        "background": {
            "N": 124, 
            "value": 23.35675048828125, 
            "delta": 0.900752067565918
        }, 
        "date": "2004-01-24"
    }
}