{
    "info": {
        "region": "261-3018-forma.reg", 
        "description": "JSON data file for stationary bowshock arcs", 
        "history": [
            "Initially created by find-xy-shell.py: <angel@crya> 2014-03-12 15:49", 
            "Circle fits added by fit-circle-shell.py: <angel@crya> 2014-03-12 15:49", 
            "Image Bally_07 added by extract-image.py: <angel@crya> 2014-03-12 15:50", 
            "Image Robberto_WFPC2_f656n_19 added by extract-image.py: <angel@crya> 2014-03-12 15:50", 
            "Shell data for Robberto_WFPC2_f656n_19 added/modified by arc_brightness.py: <angel@crya> 2014-03-12 15:54", 
            "Shell data for Bally_07 added/modified by arc_brightness.py: <angel@crya> 2014-03-12 15:54", 
            "Plot limits modified for Robberto_WFPC2_f656n_19 plot-image.py: <angel@crya> 2014-03-12 16:00", 
            "Plot limits modified for Bally_07 plot-image.py: <angel@crya> 2014-05-08 22:36", 
            "Plot limits modified for Bally_07 plot-image.py: <will@mac> 2014-05-14 10:03", 
            "Plot limits modified for Bally_07 plot-image.py: <will@mac> 2014-05-14 10:04", 
            "Shell data for Robberto_WFPC2_f656n_19 added/modified by arc_brightness.py: <angel@crya> 2014-07-05 17:54", 
            "Shell data for Bally_07 added/modified by arc_brightness.py: <angel@crya> 2014-07-05 17:54", 
            "Shell data for Robberto_WFPC2_f656n_19 added/modified by arc_brightness.py: <angel@crya> 2014-07-22 17:34", 
            "Shell data for Bally_07 added/modified by arc_brightness.py: <angel@crya> 2014-07-22 17:34", 
            "Image WFC_mosaic_f547 added by extract-image.py: <angel@crya> 2014-07-30 17:42", 
            "Shell data for Robberto_WFPC2_f656n_19 added/modified by arc_brightness.py: <angel@crya> 2014-07-30 17:42", 
            "Image WFC_mosaic_f502 added by extract-image.py: <angel@crya> 2014-07-31 16:46", 
            "Shell data for Robberto_WFPC2_f656n_19 added/modified by arc_brightness.py: <angel@crya> 2014-07-31 16:47"
        ]
    }, 
    "star": {
        "Dec_dg": -5.505004861111111, 
        "D": 440.4001905014583, 
        "PA": 340.6371735973615, 
        "RA": "5:35:26.16875", 
        "Dec": "-5:30:18.01750", 
        "RA_dg": 83.85903645833334, 
        "id": "261-3018"
    }, 
    "help": {
        "arcs": {
            "PA0": "[deg] Position angle of symmetry axis", 
            "R0": "[arcsec] Radius along symmetry axis", 
            "h": "[arcsec] Bowshock width along symmetry axis", 
            "Y": "(list) [arcsec] Offsets from star perpendicular to axis of shell points", 
            "R": "(list) [arcsec] Radii of shell points from star", 
            "X": "(list) [arcsec] Offsets from star parallel to axis of shell points", 
            "y": "(list) [arcsec] Dec offsets from star of shell points", 
            "x": "(list) [arcsec] RA offsets from star of shell points", 
            "theta": "(list) [deg] Angle from axis of shell points"
        }, 
        "star": {
            "Dec_dg": "[deg] Declination of source", 
            "D": "[arcsec] Distance of th^1 C from source", 
            "PA": "[deg] Position Angle of th^1 C from source", 
            "RA": "[HH:MM:SS] Right ascension of source", 
            "Dec": "[deg:arcmin:arcsec] Declination of source", 
            "RA_dg": "[deg] Right ascension of source", 
            "id": "Source identifier deduced from region filename"
        }, 
        "thickness": {
            "h0": "Shell thickness on axis: h0 = R0(outer) - R0(inner)"
        }, 
        "brightness": {
            "shell": "Trimean brightness and interquartile (difference between quartiles) of shell", 
            "shell center": "Trimean brightness and interquartile (difference between quartiles) of shell center", 
            "background": "Trimean brightness and interquartile (difference between quartiles) of background"
        }
    }, 
    "thickness": {
        "h0": 2.471925333599569
    }, 
    "Robberto_WFPC2_f656n_19": {
        "shell": {
            "N": 8141, 
            "value": 0.012158551486209035, 
            "delta": 0.0008816355839371681
        }, 
        "extracted FITS file": "261-3018-Robberto_WFPC2_f656n_19-extract.fits", 
        "original FITS file": "$LARGE_FITS_DIR/wfpc2/hlsp_orion_hst_wfpc2_19_f656n_v1_sci.fits", 
        "filter": "F656N", 
        "binned": {
            "theta": [
                -57.5, 
                -52.5, 
                -47.5, 
                -42.5, 
                -37.5, 
                -32.5, 
                -27.5, 
                -22.5, 
                -17.5, 
                -12.5, 
                -7.5, 
                -2.5, 
                2.5, 
                7.5, 
                12.5, 
                17.5, 
                22.5, 
                27.5, 
                32.5, 
                37.5, 
                42.5, 
                47.5, 
                52.5, 
                57.5
            ], 
            "shell": [
                0.012595558830071241, 
                0.012581993360072374, 
                0.012624133145436645, 
                0.012681823456659913, 
                0.012440955964848399, 
                0.012570941064041108, 
                0.012411764124408364, 
                0.0123827526695095, 
                0.012343371054157615, 
                0.012347681447863579, 
                0.012193273811135441, 
                0.012317914632149041, 
                0.011972127540502697, 
                0.01220522413495928, 
                0.01216375851072371, 
                0.012191049172542989, 
                0.012166548054665327, 
                0.012318875989876688, 
                0.012154139403719455, 
                0.011957084177993238, 
                0.011821655789390206, 
                0.011988217185717076, 
                0.012042155838571489, 
                0.012121183855924755
            ], 
            "background": [
                0.011649892723653466, 
                0.011631006665993482, 
                0.011822553933598101, 
                0.011634428170509636, 
                0.011756120016798377, 
                0.011659619631245732, 
                0.011730422673281282, 
                0.011731584323570132, 
                0.011758025619201362, 
                0.011650426662527025, 
                0.011646148457657546, 
                0.011608880071435124, 
                0.011541456915438175, 
                0.011489119846373796, 
                0.011588573921471834, 
                0.011441954062320292, 
                0.01133397308876738, 
                0.011413604603148997, 
                0.01135265565244481, 
                0.011683930410072207, 
                0.011751110199838877, 
                0.011740638699848205, 
                0.011663768440485001, 
                0.011521607171744108
            ], 
            "background N": [
                1258, 
                1008, 
                826, 
                696, 
                589, 
                521, 
                464, 
                419, 
                390, 
                368, 
                352, 
                350, 
                345, 
                355, 
                369, 
                394, 
                420, 
                462, 
                514, 
                589, 
                688, 
                818, 
                1001, 
                1249
            ], 
            "background sigma": [
                0.00059878030404210251, 
                0.00055646730847936255, 
                0.00067104571701170641, 
                0.0006409243265403364, 
                0.0005729143077539779, 
                0.00066187249900111515, 
                0.00051943165757478173, 
                0.0006711568698753856, 
                0.00057543388772911556, 
                0.00069171566211805838, 
                0.00064609966600837998, 
                0.00064905936990025963, 
                0.00053146671662988301, 
                0.00055304556077371094, 
                0.0005325119677827418, 
                0.00051821708816218801, 
                0.00058353234039478408, 
                0.0005368486554423737, 
                0.00057121404865443824, 
                0.00057935288916187845, 
                0.00060537612187672933, 
                0.00055535888659963024, 
                0.00057200920586401892, 
                0.00066525748341489767
            ]
        }, 
        "camera": "WFPC2", 
        "plot limits": {
            "max": 0.014906507451087236, 
            "min": 0.009174776263535023
        }, 
        "shell center": {
            "N": 4063, 
            "value": 0.012261600699275732, 
            "delta": 0.0008247476071119308
        }, 
        "background": {
            "N": 8285, 
            "value": 0.01160521525889635, 
            "delta": 0.0008101463317871094
        }, 
        "date": "2005-04-09"
    }, 
    "inner": {
        "PA0": 357.1300565732907, 
        "x": [
            -1.8514213495476046, 
            -0.6270943281957768, 
            0.9854339440894074, 
            1.8812829842054073
        ], 
        "R0": 2.514353225539292, 
        "xc": 0.06176304060857236, 
        "yc": -1.0715973549969893, 
        "Y": [
            -1.7509639462459248, 
            -0.5036387054673539, 
            1.103862928424799, 
            1.9800628219994119
        ], 
        "PAc": -3.298674444877183, 
        "Rc": 3.585786576319018, 
        "y": [
            1.9600000000000506, 
            2.449999999999264, 
            2.3900000000004695, 
            2.019999999998845
        ], 
        "X": [
            2.0502405401580983, 
            2.4783251099899855, 
            2.337662656033859, 
            1.923272442373119
        ], 
        "R": [
            2.696175256462545, 
            2.5289814741218857, 
            2.585184724186233, 
            2.7603669442043635
        ], 
        "theta": [
            -40.49827258637008, 
            -11.487073843624472, 
            25.27705435364782, 
            45.833548564953766
        ]
    }, 
    "WFC_mosaic_f502": {
        "filter": "F547M", 
        "original FITS file": "$SMALL_FITS_DIR/mosaicf502-fixw-align.fits", 
        "camera": "WFPC2", 
        "date": "1995-03-21", 
        "extracted FITS file": "261-3018-WFC_mosaic_f502-extract.fits"
    }, 
    "outer": {
        "PA0": 1.7149043810596487, 
        "x": [
            -12.362716753295258, 
            -9.973785979716245, 
            -6.7636602527612215, 
            -2.3142766868390248, 
            0.8659874054581972, 
            4.1358364017288265, 
            8.017848908770851, 
            10.406779682349864, 
            12.885295359902283, 
            16.423899068093135, 
            19.798263785761556, 
            22.635119079398567, 
            25.20321966111536, 
            27.338326540007568
        ], 
        "R0": 4.986278559138861, 
        "xc": 0.9860911300537543, 
        "yc": -28.458818332290203, 
        "Y": [
            -12.396083743097595, 
            -10.064185054152517, 
            -6.89589756275647, 
            -2.4625721765579165, 
            0.7171652924993513, 
            3.996921731963729, 
            7.890961600526482, 
            10.31204054161058, 
            12.819671636503529, 
            16.386317433181834, 
            19.7995712537483, 
            22.681242385037006, 
            25.286199087208306, 
            27.466735372998734
        ], 
        "PAc": -1.9844908749256982, 
        "Rc": 33.287543481125375, 
        "y": [
            1.300000000000523, 
            3.169999999997586, 
            4.519999999997637, 
            4.989999999998318, 
            4.9600000000005195, 
            4.579999999999629, 
            4.119999999998214, 
            3.009999999999735, 
            2.0000000000003126, 
            1.0099999999994225, 
            -0.3400000000006287, 
            -1.8799999999995265, 
            -3.150000000002251, 
            -4.700000000000415
        ], 
        "X": [
            0.9294478771400457, 
            2.8701020826692116, 
            4.315564484367021, 
            4.918507381154636, 
            4.983694225135777, 
            4.7017187719405245, 
            4.358098913847616, 
            3.3200878339508035, 
            2.384712906021926, 
            1.5010534893568959, 
            0.2526402547930964, 
            -1.2017735268145406, 
            -2.3943510620858697, 
            -3.879761069672474
        ], 
        "R": [
            12.43087951523176, 
            10.465433902575136, 
            8.134955440244317, 
            5.5005432989141925, 
            5.035030703622112, 
            6.171024448327996, 
            9.014449574092875, 
            10.833335744680323, 
            13.039587283036246, 
            16.454925116782192, 
            19.801183018461245, 
            22.713058264763717, 
            25.399306708775455, 
            27.73939613632723
        ], 
        "theta": [
            -85.71203435623536, 
            -74.08292168561889, 
            -57.96100004203782, 
            -26.595968511709124, 
            8.188781781188798, 
            40.36779625653338, 
            61.08857017159124, 
            72.15340089804376, 
            79.46229488269375, 
            84.76608017591444, 
            89.26895210844452, 
            93.03300062368643, 
            95.40921111417293, 
            98.04001449219152
        ]
    }, 
    "WFC_mosaic_f547": {
        "filter": "F547M", 
        "original FITS file": "$SMALL_FITS_DIR/mosaicf547-fixw-align.fits", 
        "camera": "WFPC2", 
        "date": "1995-03-21", 
        "extracted FITS file": "261-3018-WFC_mosaic_f547-extract.fits"
    }, 
    "Bally_07": {
        "shell": {
            "N": 6746, 
            "value": 1.2977020293474197, 
            "delta": 0.05062222480773926
        }, 
        "extracted FITS file": "261-3018-Bally_07-extract.fits", 
        "original FITS file": "$LARGE_FITS_DIR/Bally-ACS/j8oc07010_wcs.fits", 
        "filter": "F658N", 
        "binned": {
            "theta": [
                -57.5, 
                -52.5, 
                -47.5, 
                -42.5, 
                -37.5, 
                -32.5, 
                -27.5, 
                -22.5, 
                -17.5, 
                -12.5, 
                -7.5, 
                -2.5, 
                2.5, 
                7.5, 
                12.5, 
                17.5, 
                22.5, 
                27.5, 
                32.5, 
                37.5, 
                42.5, 
                47.5, 
                52.5, 
                57.5
            ], 
            "shell": [
                1.3413488268852234, 
                1.3493433594703674, 
                1.3529407680034637, 
                1.341175153851509, 
                1.3407941907644272, 
                1.3300977498292923, 
                1.3263160362839699, 
                1.3228455036878586, 
                1.3181123733520508, 
                1.3169219270348549, 
                1.3042286336421967, 
                1.303265631198883, 
                1.2948185205459595, 
                1.2953369244933128, 
                1.2952328622341156, 
                1.2959723845124245, 
                1.2876605093479156, 
                1.2896112501621246, 
                1.2778705582022667, 
                1.2713257521390915, 
                1.2714204862713814, 
                1.2743966281414032, 
                1.2881714552640915, 
                1.2964564636349678
            ], 
            "background": [
                1.2467136681079865, 
                1.2515318095684052, 
                1.2606980353593826, 
                1.2542010098695755, 
                1.2541868090629578, 
                1.2466032803058624, 
                1.2433797419071198, 
                1.2372130751609802, 
                1.2538401186466217, 
                1.2442639470100403, 
                1.2444216310977936, 
                1.234715312719345, 
                1.2247360199689865, 
                1.224584698677063, 
                1.217052884399891, 
                1.2061847150325775, 
                1.1942487955093384, 
                1.18715800344944, 
                1.1965013816952705, 
                1.2166928872466087, 
                1.2348021864891052, 
                1.2386797964572906, 
                1.237299770116806, 
                1.2206629067659378
            ], 
            "background N": [
                1042, 
                835, 
                688, 
                572, 
                493, 
                429, 
                381, 
                351, 
                325, 
                303, 
                291, 
                289, 
                287, 
                292, 
                302, 
                321, 
                346, 
                379, 
                422, 
                484, 
                571, 
                677, 
                831, 
                1039
            ], 
            "background sigma": [
                0.028551058713614443, 
                0.03051114902344675, 
                0.0307942864348082, 
                0.026149118510895977, 
                0.024393648886459254, 
                0.025804652334401924, 
                0.027902909105739733, 
                0.023951003663765895, 
                0.02812454101201143, 
                0.028816212834335428, 
                0.02572017063488209, 
                0.029592896576050725, 
                0.02569078761700516, 
                0.0256300774417226, 
                0.023405164398588973, 
                0.024026294885513697, 
                0.02704275991925824, 
                0.022033772793543547, 
                0.03298906531524699, 
                0.03296516123604185, 
                0.03215659802455482, 
                0.027850063858550548, 
                0.02396390568063817, 
                0.038861979444027354
            ]
        }, 
        "camera": "ACS", 
        "plot limits": {
            "max": 1.5, 
            "min": 1.0
        }, 
        "shell center": {
            "N": 3376, 
            "value": 1.3046922609210014, 
            "delta": 0.04766693711280823
        }, 
        "background": {
            "N": 6838, 
            "value": 1.2304775640368462, 
            "delta": 0.047934144735336304
        }, 
        "date": "2004-01-24"
    }
}